Metadata-Version: 2.1
Name: tfidftransformation
Version: 0.0.1
Summary: tfidftransformation
Author: Oguz Aktas
